growatt_monitor/__init__.py
growatt_monitor/settings.py
growatt_monitor/version.py
growatt_monitor-1.0.0.dist-info/entry_points.txt
growatt_monitor-1.0.0.dist-info/LICENSE
growatt_monitor-1.0.0.dist-info/WHEEL
growatt_monitor-1.0.0.dist-info/METADATA
growatt_monitor-1.0.0.dist-info/RECORD
